Workbook

Sheet DataTiming
A1: planning horizon T | B1: 250 | C1: weeks | D1: (5 years with 50 weeks per year) | G1: This is slightly less than the time it will take for a new drug to go through the three stages of clinical trials and roughly the time it will take to build and qualify new capacity.
A2: discount factor α | B2: 0.999 | C2: per week | D2: (or 0,95 per year)
A3: construction time sp0 | B3: 250 | C3: weeks
A4: construction time ss0 | B4: =3*4 -> 12 | C4: weeks
A5: construction cost cp | B5: 1000000 | C5: $/week | G5: total cost p | H5: =B5*B3+B7 -> 260000000
A6: construction cost cp | B6: 500000 | C6: $/week | G6: total cost s | H6: =B6*B4+B8 -> 11000000
A7: set up cost Kp | B7: 10000000 | C7: $
A8: set up cost Ks | B8: 5000000 | C8: $
A9: penalty costs p | B9: 20000000 | C9: $/week
A10: gamma 0
A11: zeta 0
A12: gamma c | B12: =200+B10 -> 200
A13: capacity demand | B13: =250*300 -> 75000 | C13: tons/year

Sheet F
A1: IF | B1: 1 | C1: 0 | D1: 0 | E1: 0
A2: S_start | B2: 0 | C2: 1 | D2: 1 | E2: 0
A3: C_final | B3: 0 | C3: 1 | D3: 0 | E3: 1
A5: F | B5: IF | C5: EF | D5: S_start | E5: C_final
A6: 1 | B6: 1 | C6: 0 | D6: 0 | E6: 0
A7: 2 | B7: 1 | C7: 0 | D7: 0 | E7: 0
A8: 3 | B8: 1 | C8: 0 | D8: 0 | E8: 0
A9: 4 | B9: 1 | C9: 0 | D9: 0 | E9: 0
A10: 5 | B10: 1 | C10: 0 | D10: 0 | E10: 0
A11: 6 | B11: 1 | C11: 0 | D11: 0 | E11: 0
A12: 7 | B12: 1 | C12: 0 | D12: 0 | E12: 0
A13: 8 | B13: 1 | C13: 0 | D13: 0 | E13: 0
A14: 9 | B14: 0 | C14: 1 | D14: 1 | E14: 0
A15: 10 | B15: 0 | C15: 1 | D15: 1 | E15: 0
A16: 11 | B16: 0 | C16: 1 | D16: 0 | E16: 1
A17: 12 | B17: 0 | C17: 1 | D17: 0 | E17: 1

Sheet F in N
A1: f/n | B1: 1 | C1: 2 | D1: 3 | E1: 4
A2: 1 | B2: 1 | C2: 0 | D2: 0 | E2: 0
A3: 2 | B3: 0 | C3: 1 | D3: 0 | E3: 0
A4: 3 | B4: 0 | C4: 0 | D4: 1 | E4: 0
A5: 4 | B5: 0 | C5: 0 | D5: 0 | E5: 1
A6: 5 | B6: 1 | C6: 0 | D6: 0 | E6: 0
A7: 6 | B7: 0 | C7: 1 | D7: 0 | E7: 0
A8: 7 | B8: 0 | C8: 0 | D8: 1 | E8: 0
A9: 8 | B9: 0 | C9: 0 | D9: 0 | E9: 1
A10: 9 | B10: 1 | C10: 0 | D10: 0 | E10: 0
A11: 10 | B11: 0 | C11: 0 | D11: 0 | E11: 1
A12: 11 | B12: 0 | C12: 0 | D12: 1 | E12: 0
A13: 12 | B13: 0 | C13: 1 | D13: 0 | E13: 0

Sheet IMf
A1: f/i | B1: 1 | C1: 2 | D1: 3 | E1: 4 | F1: 5
A2: 1 | B2: 1 | C2: 1 | D2: 0 | E2: 0 | F2: 0
A3: 2 | B3: 1 | C3: 1 | D3: 0 | E3: 0 | F3: 0
A4: 3 | B4: 1 | C4: 1 | D4: 0 | E4: 0 | F4: 0
A5: 4 | B5: 1 | C5: 1 | D5: 0 | E5: 0 | F5: 0
A6: 5 | B6: 0 | C6: 0 | D6: 1 | E6: 1 | F6: 0
A7: 6 | B7: 0 | C7: 0 | D7: 1 | E7: 1 | F7: 0
A8: 7 | B8: 0 | C8: 0 | D8: 1 | E8: 1 | F8: 0
A9: 8 | B9: 0 | C9: 0 | D9: 1 | E9: 1 | F9: 0
A10: 9 | B10: 0 | C10: 0 | D10: 0 | E10: 0 | F10: 0
A11: 10 | B11: 0 | C11: 0 | D11: 0 | E11: 0 | F11: 0
A12: 11 | B12: 0 | C12: 0 | D12: 0 | E12: 0 | F12: 1
A13: 12 | B13: 0 | C13: 0 | D13: 0 | E13: 0 | F13: 1

Sheet OMf
A1: f/i | B1: 1 | C1: 2 | D1: 5 | E1: 6 | F1: 8
A2: 1 | B2: 0 | C2: 0 | D2: 1 | E2: 0 | F2: 0
A3: 2 | B3: 0 | C3: 0 | D3: 1 | E3: 0 | F3: 0
A4: 3 | B4: 0 | C4: 0 | D4: 1 | E4: 0 | F4: 0
A5: 4 | B5: 0 | C5: 0 | D5: 1 | E5: 0 | F5: 0
A6: 5 | B6: 0 | C6: 0 | D6: 0 | E6: 0 | F6: 1
A7: 6 | B7: 0 | C7: 0 | D7: 0 | E7: 0 | F7: 1
A8: 7 | B8: 0 | C8: 0 | D8: 0 | E8: 0 | F8: 1
A9: 8 | B9: 0 | C9: 0 | D9: 0 | E9: 0 | F9: 1
A10: 9 | B10: 1 | C10: 1 | D10: 0 | E10: 0 | F10: 0
A11: 10 | B11: 1 | C11: 1 | D11: 0 | E11: 0 | F11: 0
A12: 11 | B12: 0 | C12: 0 | D12: 0 | E12: 0 | F12: 0
A13: 12 | B13: 0 | C13: 0 | D13: 0 | E13: 0 | F13: 0

Sheet Const.
A1: Production days per year | B1: 300 | C1: days/year | D1: alle Kosten bzw. Transportmengen müssen zum Zeitpunkt t auf ein Jahr hochgerechnet werden!
A2: Project life Lf | B2: 15 | C2: years
A3: Budget for primary expansion (t=1) | B3: 300000000 | C3: $
A4: Budget fo seconcary expansion (t=1+∆t*) | B4: 50000000 | C4: $

Sheet TRn
A1: Nation n | B1: corporate tax TRn
A2: 1 | B2: 0.27
A3: 2 | B3: 0.42
A4: 3 | B4: 0.15
A5: 4 | B5: 0.28

Sheet MassBalance
A1: f/i | B1: 1 | C1: 2 | D1: 5 | E1: 6 | F1: 8
A2: 1 | B2: 0.6 | C2: 0.4 | D2: 1 | E2: 0 | F2: 0
A3: 2 | B3: 0.6 | C3: 0.4 | D3: 1 | E3: 0 | F3: 0
A4: 3 | B4: 0.6 | C4: 0.4 | D4: 1 | E4: 0 | F4: 0
A5: 4 | B5: 0.6 | C5: 0.4 | D5: 1 | E5: 0 | F5: 0
A6: 5 | B6: 0 | C6: 0 | D6: 0.6 | E6: 0.4 | F6: 1
A7: 6 | B7: 0 | C7: 0 | D7: 0.6 | E7: 0.4 | F7: 1
A8: 7 | B8: 0 | C8: 0 | D8: 0.6 | E8: 0.4 | F8: 1
A9: 8 | B9: 0 | C9: 0 | D9: 0.6 | E9: 0.4 | F9: 1
A10: 9 | B10: 0 | C10: 0 | D10: 0 | E10: 0 | F10: 0
A11: 10 | B11: 0 | C11: 0 | D11: 0 | E11: 0 | F11: 0
A12: 11 | B12: 0 | C12: 0 | D12: 0 | E12: 0 | F12: 0
A13: 12 | B13: 0 | C13: 0 | D13: 0 | E13: 0 | F13: 0

Sheet DataF
A1: Facility f | B1: max cap. Quf [tons/year] | C1: min expansion qLf [tons/year] | D1: min production XLf [tons/year] | E1: MCf [$/ton]
A2: 1 | B2: 75000 | C2: 18000 | D2: 15000 | E2: 1120
A3: 2 | B3: 90000 | C3: 18000 | D3: 15000 | E3: 1120
A4: 3 | B4: 84000 | C4: 18000 | D4: 15000 | E4: 1120
A5: 4 | B5: 96000 | C5: 18000 | D5: 15000 | E5: 1120
A6: 5 | B6: 24000 | C6: 6000 | D6: 3000 | E6: 930
A7: 6 | B7: 27000 | C7: 6000 | D7: 3000 | E7: 930
A8: 7 | B8: 21000 | C8: 6000 | D8: 3000 | E8: 930
A9: 8 | B9: 27000 | C9: 6000 | D9: 3000 | E9: 930

Sheet Dict (i=8)
A1: Sum | C1: =250*300 -> 75000 | D1: =SUM(D3:D6) -> 36000
A2: Customer c | B2: Percentage of D | C2: D Monopoly [tons/year] | D2: D Regular Market [tons/year] | E2: Percentage of Monopoly D
A3: 1 | B3: 0.3 | C3: =B3*$C$1 -> 22500 | D3: =C3*E3 -> 15750 | E3: 0.7
A4: 2 | B4: 0.2 | C4: =B4*$C$1 -> 15000 | D4: =C4*E4 -> 4500 | E4: 0.3
A5: 3 | B5: 0.4 | C5: =B5*$C$1 -> 30000 | D5: =C5*E5 -> 12000 | E5: 0.4
A6: 4 | B6: 0.1 | C6: =B6*$C$1 -> 7500 | D6: =C6*E6 -> 3750 | E6: 0.5

Sheet Sis
A1: i/s [tons/year] | B1: 21 | C1: 22 | D1: 23 | E1: 24 | F1: 25
A2: 1 | B2: 60000 | C2: 33000 | D2: 24000 | E2: 18000 | F2: 51000
A3: 2 | B3: 45000 | C3: 30000 | D3: 36000 | E3: 24000 | F3: 45000
A4: 6 | B4: 21000 | C4: 51000 | D4: 45000 | E4: 33000 | F4: 24000

Sheet Pif
A1: f/i [$/ton] | B1: 1 | C1: 2 | D1: 3 | E1: 4 | F1: 5 | G1: 6 | H1: 7
A2: 1 | F2: 440
A3: 2 | F3: 440
A4: 3 | F4: 440
A5: 4 | F5: 440
A6: 5
A7: 6
A8: 7
A9: 8
A10: 9 | B10: 510 | C10: 2280 | D10: 1410 | E10: 1550 | G10: 780 | H10: 990
A11: 10 | B11: 1780 | C11: 1170 | D11: 750 | E11: 1210 | G11: 1580 | H11: 1410
A12: 11
A13: 12

Sheet CIF1sf
A1: s/f [$/ton] | B1: 1 | C1: 2 | D1: 3 | E1: 4
A2: 9 | B2: 15 | C2: 39 | D2: 39 | E2: 41
A3: 10 | B3: 32 | C3: 45 | D3: 55 | E3: 13

Sheet CIF2sf
A1: s/f [$/ton] | B1: 1 | C1: 2 | D1: 3 | E1: 4
A2: 9 | B2: =1.2*CIF1sf!B2 -> 18 | C2: =1.2*CIF1sf!C2 -> 46.8 | D2: =1.2*CIF1sf!D2 -> 46.8 | E2: =1.2*CIF1sf!E2 -> 49.2
A3: 10 | B3: =1.2*CIF1sf!B3 -> 38.4 | C3: =1.2*CIF1sf!C3 -> 54 | D3: =1.2*CIF1sf!D3 -> 66 | E3: =1.2*CIF1sf!E3 -> 15.6

Sheet CIF3sf
A1: s/f [$/ton] | B1: 1 | C1: 2 | D1: 3 | E1: 4
A2: 9 | B2: =0.8*CIF1sf!B2 -> 12 | C2: =0.8*CIF1sf!C2 -> 31.2 | D2: =0.8*CIF1sf!D2 -> 31.2 | E2: =0.8*CIF1sf!E2 -> 32.8
A3: 10 | B3: =0.8*CIF1sf!B3 -> 25.6 | C3: =0.8*CIF1sf!C3 -> 36 | D3: =0.8*CIF1sf!D3 -> 44 | E3: =0.8*CIF1sf!E3 -> 10.4

Sheet CIF4sf
A1: s/f [$/ton] | B1: 1 | C1: 2 | D1: 3 | E1: 4
A2: 9 | B2: =1.5*CIF1sf!B2 -> 22.5 | C2: =1.5*CIF1sf!C2 -> 58.5 | D2: =1.5*CIF1sf!D2 -> 58.5 | E2: =1.5*CIF1sf!E2 -> 61.5
A3: 10 | B3: =1.5*CIF1sf!B3 -> 48 | C3: =1.5*CIF1sf!C3 -> 67.5 | D3: =1.5*CIF1sf!D3 -> 82.5 | E3: =1.5*CIF1sf!E3 -> 19.5

Sheet CIF5sf
A1: s/f [$/ton] | B1: 8 | C1: 9 | D1: 10 | E1: 11
A2: 1 | B2: 0 | C2: 13 | D2: 23 | E2: 37
A3: 2 | B3: 38 | C3: 0 | D3: 25 | E3: 9
A4: 3 | B4: 28 | C4: 39 | D4: 0 | E4: 31
A5: 4 | B5: 25 | C5: 23 | D5: 27 | E5: 0

Sheet CIF6sf
A1: s/f [$/ton] | B1: 1 | C1: 2 | D1: 3 | E1: 4
A2: 9 | B2: =0.4*CIF1sf!B2 -> 6 | C2: =0.4*CIF1sf!C2 -> 15.6 | D2: =0.4*CIF1sf!D2 -> 15.6 | E2: =0.4*CIF1sf!E2 -> 16.4
A3: 10 | B3: =0.4*CIF1sf!B3 -> 12.8 | C3: =0.4*CIF1sf!C3 -> 18 | D3: =0.4*CIF1sf!D3 -> 22 | E3: =0.4*CIF1sf!E3 -> 5.2

Sheet CIF7sf
A1: s/f [$/ton] | B1: 1 | C1: 2 | D1: 3 | E1: 4
A2: 9 | B2: =0.8*CIF1sf!B2 -> 12 | C2: =0.8*CIF1sf!C2 -> 31.2 | D2: =0.8*CIF1sf!D2 -> 31.2 | E2: =0.8*CIF1sf!E2 -> 32.8
A3: 10 | B3: =0.8*CIF1sf!B3 -> 25.6 | C3: =0.8*CIF1sf!C3 -> 36 | D3: =0.8*CIF1sf!D3 -> 44 | E3: =0.8*CIF1sf!E3 -> 10.4

Sheet IDisf
A1: s/f | B1: 1 | C1: 2 | D1: 3 | E1: 4 | F1: 5 | G1: 6 | H1: 7 | I1: 8
A2: 1 | B2: 0 | C2: 0 | D2: 0 | E2: 0 | F2: 0 | G2: 0.15 | H2: 0.4 | I2: 0.75
A3: 2 | B3: 0 | C3: 0 | D3: 0 | E3: 0 | F3: 0.05 | G3: 0 | H3: 0.4 | I3: 0.75
A4: 3 | B4: 0 | C4: 0 | D4: 0 | E4: 0 | F4: 0.05 | G4: 0.15 | H4: 0 | I4: 0.75
A5: 4 | B5: 0 | C5: 0 | D5: 0 | E5: 0 | F5: 0.05 | G5: 0.15 | H5: 0.4 | I5: 0
A6: 9 | B6: 0 | C6: 0.15 | D6: 0.4 | E6: 0.75 | F6: 0 | G6: 0.15 | H6: 0.4 | I6: 0.75
A7: 10 | B7: 0.05 | C7: 0.15 | D7: 0.4 | E7: 0 | F7: 0.05 | G7: 0.15 | H7: 0.4 | I7: 0
